base_http_client/__init__.py
base_http_client/client.py
base_http_client/exceptions.py
base_http_client/handlers/__init__.py
base_http_client/handlers/base.py
base_http_client/handlers/json.py
base_http_client/handlers/msgspec.py
base_http_client/handlers/pydantic.py
base_http_client/py.typed
base_http_client/timeout.py
test_http_service/__init__.py
test_http_service/handlers.py
test_http_service/models.py
test_http_service/responses.py
test_http_service/serialization.py
test_http_service/service.py
base_http_client-0.2.5.dist-info/METADATA
base_http_client-0.2.5.dist-info/WHEEL
base_http_client-0.2.5.dist-info/RECORD
