Metadata-Version: 2.1
Name: base-http-client
Version: 0.2.5
Summary: Typical HTTP Client based on aiohttp
Home-page: https://github.com/andy-takker/base_http_client
License: MIT
Keywords: aiohttp,http,client
Author: Sergey Natalenko
Author-email: sergey.natalenko@mail.ru
Requires-Python: >=3.10,<4.0
Classifier: Development Status :: 4 - Beta
Classifier: Framework :: AsyncIO
Classifier: Framework :: Pytest
Classifier: Framework :: aiohttp
Classifier: Intended Audience :: Developers
Classifier: Intended Audience :: Information Technology
Classifier: Intended Audience :: System Administrators
Classifier: License :: OSI Approved :: MIT License
Classifier: Operating System :: OS Independent
Classifier: Programming Language :: Python
Classifier: Programming Language :: Python :: 3
Classifier: Programming Language :: Python :: 3.10
Classifier: Programming Language :: Python :: 3.11
Classifier: Programming Language :: Python :: 3.12
Classifier: Programming Language :: Python :: 3.13
Classifier: Topic :: Internet
Classifier: Topic :: Internet :: WWW/HTTP
Classifier: Topic :: Software Development
Classifier: Topic :: Software Development :: Libraries
Classifier: Topic :: Software Development :: Libraries :: Python Modules
Provides-Extra: msgspec
Provides-Extra: orjson
Provides-Extra: pydantic
Requires-Dist: aiohttp (>=3.9.5,<4.0.0)
Requires-Dist: msgspec (>=0.18.6,<0.19.0) ; extra == "msgspec"
Requires-Dist: orjson (>=3.10.6,<4.0.0) ; extra == "orjson"
Requires-Dist: pydantic (>=2.8.2,<3.0.0) ; extra == "pydantic"
Project-URL: Source, https://github.com/andy-takker/base_http_client
